setup.py
markovy/__init__.py
markovy.egg-info/PKG-INFO
markovy.egg-info/SOURCES.txt
markovy.egg-info/dependency_links.txt
markovy.egg-info/not-zip-safe
markovy.egg-info/requires.txt
markovy.egg-info/top_level.txt